.gitignore
LICENSE
README.md
requirements.txt
setup.cfg
setup.py
aiorq/__init__.py
aiorq/cli.py
aiorq/connections.py
aiorq/constants.py
aiorq/cron.py
aiorq/demo.py
aiorq/exception.py
aiorq/jobs.py
aiorq/logs.py
aiorq/serialize.py
aiorq/specs.py
aiorq/typing_.py
aiorq/utils.py
aiorq/version.py
aiorq/worker.py
aiorq.egg-info/PKG-INFO
aiorq.egg-info/SOURCES.txt
aiorq.egg-info/dependency_links.txt
aiorq.egg-info/entry_points.txt
aiorq.egg-info/requires.txt
aiorq.egg-info/top_level.txt
aiorq.egg-info/zip-safe
aiorq/app_server/__init__.py
aiorq/app_server/depends.py
aiorq/app_server/main.py
aiorq/app_server/schemas.py
aiorq/app_server/config/__init__.py
aiorq/app_server/config/development_config.py
aiorq/app_server/db/__init__.py
aiorq/app_server/db/mongodb_.py
aiorq/app_server/logger/__init__.py
aiorq/app_server/logger/logger.py
aiorq/app_server/responses/__init__.py
aiorq/app_server/responses/response_code.py
aiorq/app_server/responses/responses.py
aiorq/app_server/v1/__init__.py
aiorq/app_server/v1/index.py
aiorq/app_server/v1/job.py
aiorq/app_server/v1/setting.py
docs/.gitignore
docs/LICENSE
docs/Makefile
docs/README.md
docs/conf.py
docs/index.rst
docs/make.bat
docs/requirements.txt
docs/docs/index.md
tests/__init__.py
tests/check_tag.py
tests/conftest.py
tests/test_cli.py
tests/test_cron.py
tests/test_jobs.py
tests/test_main.py
tests/test_utils.py
tests/test_worker.py